[{"label_hash": "177482ac-8353-4547-91ff-566082acb86c", "branch_name": "main", "created_at": "2025-11-04 21:34:29", "last_edited_at": "2025-11-04 21:38:54", "dataset_hash": "3352b997-0f30-4f24-8dde-56acef69acc2", "dataset_title": "Ziyad YOLO BDI interaction", "data_title": "LapChol Case 0012 03.mp4", "data_hash": "ebbd946d-5d7a-4d4d-9c2d-7d0f8d6c5cfb", "backing_item_uuid": "ebbd946d-5d7a-4d4d-9c2d-7d0f8d6c5cfb", "data_type": "video", "is_image_sequence": null, "data_units": {"ebbd946d-5d7a-4d4d-9c2d-7d0f8d6c5cfb": {"data_hash": "ebbd946d-5d7a-4d4d-9c2d-7d0f8d6c5cfb", "data_title": "LapChol Case 0012 03.mp4", "data_type": "video/mp4", "data_sequence": 0, "labels": {"0": {"objects": [{"featureHash": "s7/A4zcg", "objectHash": "CZRQl1CH", "name": "Start of TTI", "value": "start_of_tti", "color": "#D33115", "shape": "bounding_box", "confidence": 1, "frame": 0, "createdBy": "madanilab1@gmail.com", "createdAt": "Tue, 04 Nov 2025 21:34:55 GMT", "lastEditedBy": "madanilab1@gmail.com", "lastEditedAt": "Tue, 04 Nov 2025 21:34:55 GMT", "manualAnnotation": true, "boundingBox": {"x": 0.5456048729804008, "y": 0.3236773980068514, "w": 0.09029746357908923, "h": 0.0975059227210037}}], "classifications": []}, "94": {"objects": [{"featureHash": "orS7zbRG", "objectHash": "d84ozPfn", "name": "End of TTI ", "value": "end_of_tti_", "color": "#d3b515", "shape": "bounding_box", "confidence": 1, "frame": 94, "createdBy": "madanilab1@gmail.com", "createdAt": "Tue, 04 Nov 2025 21:34:46 GMT", "lastEditedBy": "madanilab1@gmail.com", "lastEditedAt": "Tue, 04 Nov 2025 21:34:46 GMT", "manualAnnotation": true, "boundingBox": {"x": 0.48454667614220936, "y": 0.40059282822440717, "w": 0.10292147923954201, "h": 0.10811051296881255}}], "classifications": []}, "117": {"objects": [{"featureHash": "s7/A4zcg", "objectHash": "PlILxrQy", "name": "Start of TTI", "value": "start_of_tti", "color": "#D33115", "shape": "bounding_box", "confidence": 1, "frame": 117, "createdBy": "madanilab1@gmail.com", "createdAt": "Tue, 04 Nov 2025 21:35:11 GMT", "lastEditedBy": "madanilab1@gmail.com", "lastEditedAt": "Tue, 04 Nov 2025 21:35:11 GMT", "manualAnnotation": true, "boundingBox": {"x": 0.5944767031385556, "y": 0.4361291542465632, "w": 0.09796556684159086, "h": 0.10842333274013427}}], "classifications": []}, "173": {"objects": [{"featureHash": "orS7zbRG", "objectHash": "lQYgL2BH", "name": "End of TTI ", "value": "end_of_tti_", "color": "#d3b515", "shape": "bounding_box", "confidence": 1, "frame": 173, "createdBy": "madanilab1@gmail.com", "createdAt": "Tue, 04 Nov 2025 21:35:24 GMT", "lastEditedBy": "madanilab1@gmail.com", "lastEditedAt": "Tue, 04 Nov 2025 21:35:25 GMT", "manualAnnotation": true, "boundingBox": {"x": 0.4860352990826386, "y": 0.30981600636205897, "w": 0.0890584854796014, "h": 0.09050223561863238}}], "classifications": []}, "4129": {"objects": [{"featureHash": "s7/A4zcg", "objectHash": "M4CYPMM9", "name": "Start of TTI", "value": "start_of_tti", "color": "#D33115", "shape": "bounding_box", "confidence": 1, "frame": 4129, "createdBy": "madanilab1@gmail.com", "createdAt": "Tue, 04 Nov 2025 21:36:22 GMT", "lastEditedBy": "madanilab1@gmail.com", "lastEditedAt": "Tue, 04 Nov 2025 21:36:22 GMT", "manualAnnotation": true, "boundingBox": {"x": 0.1911862497202, "y": 0.4006831983805668, "w": 0.09061799522671787, "h": 0.08221251167860473}}], "classifications": []}, "4157": {"objects": [{"featureHash": "orS7zbRG", "objectHash": "q3A8DdHa", "name": "End of TTI ", "value": "end_of_tti_", "color": "#d3b515", "shape": "bounding_box", "confidence": 1, "frame": 4157, "createdBy": "madanilab1@gmail.com", "createdAt": "Tue, 04 Nov 2025 21:36:37 GMT", "lastEditedBy": "madanilab1@gmail.com", "lastEditedAt": "Tue, 04 Nov 2025 21:36:38 GMT", "manualAnnotation": true, "boundingBox": {"x": 0.28081799372344507, "y": 0.3104659763313608, "w": 0.07487804210710503, "h": 0.09212542265426878}}], "classifications": []}, "7169": {"classifications": [], "objects": []}}, "width": 1280, "height": 720, "data_fps": 30.0, "data_duration": 334.33334, "data_link": "gs://cord-ai-platform.appspot.com/cord-videos-prod/06EaLrKlAOPJwt0M0SXN535c0x33/ebbd946d-5d7a-4d4d-9c2d-7d0f8d6c5cfb"}}, "object_answers": {"d84ozPfn": {"objectHash": "d84ozPfn", "classifications": [{"name": "type of instrument", "value": "type_of_instrument", "answers": [{"name": "Cautery", "value": "cautery", "featureHash": "1seZ2DyM"}], "featureHash": "tpREpTqe", "manualAnnotation": true}], "featureHash": "orS7zbRG", "range": [[94, 94]], "createdAt": "Tue, 04 Nov 2025 21:34:46 GMT", "createdBy": "madanilab1@gmail.com", "lastEditedAt": "Tue, 04 Nov 2025 21:34:47 GMT", "lastEditedBy": "madanilab1@gmail.com"}, "CZRQl1CH": {"objectHash": "CZRQl1CH", "classifications": [{"name": "type of instrument", "value": "type_of_instrument", "answers": [{"name": "Cautery", "value": "cautery", "featureHash": "Ts6WvQr+"}], "featureHash": "yI5tM7Nm", "manualAnnotation": true}], "featureHash": "s7/A4zcg", "range": [[0, 0]], "createdAt": "Tue, 04 Nov 2025 21:34:55 GMT", "createdBy": "madanilab1@gmail.com", "lastEditedAt": "Tue, 04 Nov 2025 21:34:55 GMT", "lastEditedBy": "madanilab1@gmail.com"}, "PlILxrQy": {"objectHash": "PlILxrQy", "classifications": [{"name": "type of instrument", "value": "type_of_instrument", "answers": [{"name": "Cautery", "value": "cautery", "featureHash": "Ts6WvQr+"}], "featureHash": "yI5tM7Nm", "manualAnnotation": true}], "featureHash": "s7/A4zcg", "range": [[117, 117]], "createdAt": "Tue, 04 Nov 2025 21:35:11 GMT", "createdBy": "madanilab1@gmail.com", "lastEditedAt": "Tue, 04 Nov 2025 21:35:12 GMT", "lastEditedBy": "madanilab1@gmail.com"}, "lQYgL2BH": {"objectHash": "lQYgL2BH", "classifications": [{"name": "type of instrument", "value": "type_of_instrument", "answers": [{"name": "Cautery", "value": "cautery", "featureHash": "1seZ2DyM"}], "featureHash": "tpREpTqe", "manualAnnotation": true}], "featureHash": "orS7zbRG", "range": [[173, 173]], "createdAt": "Tue, 04 Nov 2025 21:35:24 GMT", "createdBy": "madanilab1@gmail.com", "lastEditedAt": "Tue, 04 Nov 2025 21:35:26 GMT", "lastEditedBy": "madanilab1@gmail.com"}, "M4CYPMM9": {"objectHash": "M4CYPMM9", "classifications": [{"name": "type of instrument", "value": "type_of_instrument", "answers": [{"name": "Cautery", "value": "cautery", "featureHash": "Ts6WvQr+"}], "featureHash": "yI5tM7Nm", "manualAnnotation": true}], "featureHash": "s7/A4zcg", "range": [[4129, 4129]], "createdAt": "Tue, 04 Nov 2025 21:36:22 GMT", "createdBy": "madanilab1@gmail.com", "lastEditedAt": "Tue, 04 Nov 2025 21:36:23 GMT", "lastEditedBy": "madanilab1@gmail.com"}, "q3A8DdHa": {"objectHash": "q3A8DdHa", "classifications": [{"name": "type of instrument", "value": "type_of_instrument", "answers": [{"name": "Cautery", "value": "cautery", "featureHash": "1seZ2DyM"}], "featureHash": "tpREpTqe", "manualAnnotation": true}], "featureHash": "orS7zbRG", "range": [[4157, 4157]], "createdAt": "Tue, 04 Nov 2025 21:36:37 GMT", "createdBy": "madanilab1@gmail.com", "lastEditedAt": "Tue, 04 Nov 2025 21:36:39 GMT", "lastEditedBy": "madanilab1@gmail.com"}}, "classification_answers": {}, "object_actions": {}, "label_status": "LABELLED", "is_valid": true, "video_link": "gs://cord-ai-platform.appspot.com/cord-videos-prod/06EaLrKlAOPJwt0M0SXN535c0x33/ebbd946d-5d7a-4d4d-9c2d-7d0f8d6c5cfb"}]